{
  "components": {
    "x-1851424-doli-comp": {
      "innerComponents": [],
      "actions": [
        {
          "name": "VALUE_SET",
          "action": "SEND_COMP_DATA#VALUE_SET",
          "label": "Send Component Data",
          "payload": [
            {
              "name": "mode",
              "label": "Mode",
              "type": "string"
            },
            {
              "name": "wafer",
              "label": "Wafer",
              "type": "string"
            },
            {
              "name": "selected",
              "label": "Selected",
              "type": "string"
            },
            {
              "name": "editablevalues",
              "label": "Editable",
              "type": "string"
            },
            {
              "name": "operation",
              "label": "Operation",
              "type": "string"
            },
            {
              "name": "readonly",
              "label": "Readonly",
              "type": "string"
            }
          ]
        }
      ],
      "uiBuilder": {
        "associatedTypes": [
          "global.core",
          "global.landing-page"
        ],
        "label": "Doli Wafer Component",
        "tileIcon": "./tile-icon/13.svg",
        "description": "DOLI Wafer Component",
        "category": "primitive"
      },
      "properties": [
        {
          "name": "mode",
          "label": "Mode",
          "fieldType": "string"
        },
        {
          "name": "wafer",
          "label": "Wafer",
          "fieldType": "string"
        },
        {
          "name": "selected",
          "label": "Selected",
          "fieldType": "string"
        },
        {
          "name": "editablevalues",
          "label": "Editable",
          "fieldType": "string"
        },
        {
          "name": "operation",
          "label": "Operation",
          "fieldType": "string"
        },
        {
          "name": "readonly",
          "label": "Readonly",
          "fieldType": "string"
        }
      ]
    }
  },
  "scopeName": "x_1851424_doli_c_0"
}
